counter/rtl/counter.sv
module counter #(
    parameter CNTR_WIDTH = 4
) (
    input   logic                       clk,
    input   logic                       rst_n,
    output  logic [CNTR_WIDTH - 1 : 0]  cntr 
);

    logic [CNTR_WIDTH - 1 : 0] cntr_nxt;

    always_ff@(posedge clk) begin 
        if(!rst_n)
            cntr <= '0;
        else
            cntr <= cntr_nxt;
    end 


    always_comb begin : CNTR_COMBO
        cntr_nxt = cntr + 1;
    end

    // Dump waves
    initial begin
        $dumpfile("counter_dump.vcd");
        $dumpvars(1, counter);
    end

endmodule

rtl/counter/verif/coco/counter_dump.vcd
$date
	Thu Sep 14 15:19:53 2023
$end
$version
	Icarus Verilog
$end
$timescale
	1ps
$end
$scope module counter $end
$var wire 1 ! clk $end
$var wire 1 " rst_n $end
$var parameter 32 # CNTR_WIDTH $end
$var reg 4 $ cntr [3:0] $end
$var reg 4 % cntr_nxt [3:0] $end
$upscope $end
$enddefinitions $end
$comment Show the parameter values. $end
$dumpall
b100 #
$end
#0
$dumpvars
bx %
bx $
z"
z!
$end
#1
1"
1!
#501
0!
#1001
0"
1!
#1501
0!
#2001
b1 %
b0 $
1!
#2501
0!
#3001
1"
1!
#3501
0!
#4001
b10 %
b1 $
1!
#4501
0!
#5001
b11 %
b10 $
1!
#5501
0!
#6001
b100 %
b11 $
1!
#6501
0!
#7001
b101 %
b100 $
1!
#7501
0!
#8001
b110 %
b101 $
1!
#8501
0!
#9001
b111 %
b110 $
1!
#9501
0!
#10001
b1000 %
b111 $
1!
#10501
0!
#11001
b1001 %
b1000 $
1!
#11501
0!
#12001
b1010 %
b1001 $
1!
#12501
0!
#13001
b1011 %
b1010 $
1!
#13501
0!
#14001
b1100 %
b1011 $
1!
#14501
0!
#15001
b1101 %
b1100 $
1!
#15501
0!
#16001
b1110 %
b1101 $
1!
#16501
0!
#17001
b1111 %
b1110 $
1!
#17501
0!
#18001
b0 %
b1111 $
1!
#18501
0!
#19001
b1 %
b0 $
1!
#19501
0!
#20001
b10 %
b1 $
1!
#20501
0!
#21001
b11 %
b10 $
1!
#21501
0!
#22001
b100 %
b11 $
1!
#22501
0!
#23001
b101 %
b100 $
1!
#23501
0!
#24001
b110 %
b101 $
1!
#24501
0!
#25001
b111 %
b110 $
1!
#25501
0!
#26001
b1000 %
b111 $
1!
#26501
0!
#27001
b1001 %
b1000 $
1!
#27501
0!
#28001
b1010 %
b1001 $
1!
#28501
0!
#29001
b1011 %
b1010 $
1!
#29501
0!
#30001
b1100 %
b1011 $
1!
#30501
0!
#31001
b1101 %
b1100 $
1!
#31501
0!
#32001
b1110 %
b1101 $
1!
#32501
0!
#33001
b1111 %
b1110 $
1!
#33501
0!
#34001
b0 %
b1111 $
1!
#34501
0!
#35001
b1 %
b0 $
1!
#35501
0!
#36001
b10 %
b1 $
1!
#36501
0!
#37001
b11 %
b10 $
1!
#37501
0!
#38001
b100 %
b11 $
1!
#38501
0!
#39001
b101 %
b100 $
1!
#39501
0!
#40001
b110 %
b101 $
1!
#40501
0!
#41001
b111 %
b110 $
1!
#41501
0!
#42001
b1000 %
b111 $
1!
#42501
0!
#43001
b1001 %
b1000 $
1!
#43501
0!
#44001
b1010 %
b1001 $
1!
#44501
0!
#45001
b1011 %
b1010 $
1!
#45501
0!
#46001
b1100 %
b1011 $
1!
#46501
0!
#47001
b1101 %
b1100 $
1!
#47501
0!
#48001
b1110 %
b1101 $
1!
#48501
0!
#49001
b1111 %
b1110 $
1!
#49501
0!
#50001
b0 %
b1111 $
1!
#50501
0!
#51001
b1 %
b0 $
1!
#51501
0!
#52001
b10 %
b1 $
1!
#52501
0!
#53001
b11 %
b10 $
1!
#53501
0!
#54001
b100 %
b11 $
1!
#54501
0!
#55001
b101 %
b100 $
1!
#55501
0!
#56001
b110 %
b101 $
1!
#56501
0!
#57001
b111 %
b110 $
1!
#57501
0!
#58001
b1000 %
b111 $
1!
#58501
0!
#59001
b1001 %
b1000 $
1!
#59501
0!
#60001
b1010 %
b1001 $
1!
#60501
0!
#61001
b1011 %
b1010 $
1!
#61501
0!
#62001
b1100 %
b1011 $
1!
#62501
0!
#63001
b1101 %
b1100 $
1!
#63501
0!
#64001
b1110 %
b1101 $
1!
#64501
0!
#65001
b1111 %
b1110 $
1!
#65501
0!
#66001
b0 %
b1111 $
1!
#66501
0!
#67001
b1 %
b0 $
1!
#67501
0!
#68001
b10 %
b1 $
1!
#68501
0!
#69001
b11 %
b10 $
1!
#69501
0!
#70001
b100 %
b11 $
1!
#70501
0!
#71001
b101 %
b100 $
1!
#71501
0!
#72001
b110 %
b101 $
1!
#72501
0!
#73001
b111 %
b110 $
1!
#73501
0!
#74001
b1000 %
b111 $
1!
#74501
0!
#75001
b1001 %
b1000 $
1!
#75501
0!
#76001
b1010 %
b1001 $
1!
#76501
0!
#77001
b1011 %
b1010 $
1!
#77501
0!
#78001
b1100 %
b1011 $
1!
#78501
0!
#79001
b1101 %
b1100 $
1!
#79501
0!
#80001
b1110 %
b1101 $
1!
#80501
0!
#81001
b1111 %
b1110 $
1!
#81501
0!
#82001
b0 %
b1111 $
1!
#82501
0!
#83001
b1 %
b0 $
1!
#83501
0!
#84001
b10 %
b1 $
1!
#84501
0!
#85001
b11 %
b10 $
1!
#85501
0!
#86001
b100 %
b11 $
1!
#86501
0!
#87001
b101 %
b100 $
1!
#87501
0!
#88001
b110 %
b101 $
1!
#88501
0!
#89001
b111 %
b110 $
1!
#89501
0!
#90001
b1000 %
b111 $
1!
#90501
0!
#91001
b1001 %
b1000 $
1!
#91501
0!
#92001
b1010 %
b1001 $
1!
#92501
0!
#93001
b1011 %
b1010 $
1!
#93501
0!
#94001
b1100 %
b1011 $
1!
#94501
0!
#95001
b1101 %
b1100 $
1!
#95501
0!
#96001
b1110 %
b1101 $
1!
#96501
0!
#97001
b1111 %
b1110 $
1!
#97501
0!
#98001
b0 %
b1111 $
1!
#98501
0!
#99001
b1 %
b0 $
1!
#99501
0!
#100001
b10 %
b1 $
1!
